sqliterepl/__init__.py
sqliterepl/completions.py
sqliterepl/context.py
sqliterepl/main.py
sqliterepl/meta_cmds.py
sqliterepl/utils.py
sqliterepl-2.0.0.dist-info/LICENSE
sqliterepl-2.0.0.dist-info/METADATA
sqliterepl-2.0.0.dist-info/WHEEL
sqliterepl-2.0.0.dist-info/entry_points.txt
sqliterepl-2.0.0.dist-info/top_level.txt
sqliterepl-2.0.0.dist-info/RECORD
