Metadata-Version: 2.1
Name: sqliterepl
Version: 2.0.0
Summary: SQLite REPL written in python3
Home-page: https://github.com/nl253/SQLiteREPL
Author: Norbert Logiewa
Author-email: norbertlogiewa96@gmail.com
License: MIT
Project-URL: Bug Tracker, https://github.com/nl253/SQLiteREPL/issues
Project-URL: Source Code, https://github.com/nl253/SQLiteREPL
Keywords: database sqlite3 sqlite sqliterepl REPL SQLite prompt-toolkit prompt_toolkit
Platform: UNKNOWN
Classifier: Intended Audience :: Developers
Classifier: Topic :: Database :: Front-Ends
Classifier: License :: OSI Approved :: MIT License
Classifier: Programming Language :: Python :: 3.7
Requires-Python: >=3.6
Requires-Dist: prompt-toolkit (>=2.0)
Requires-Dist: tabulate (>=0.8.1)
Requires-Dist: pygments (>=2.2.0)
